{"organizations": [], "uuid": "884497dee1537cc5b882130a2795dfa456af91d6", "thread": {"social": {"gplus": {"shares": 0}, "pinterest": {"shares": 0}, "vk": {"shares": 0}, "linkedin": {"shares": 0}, "facebook": {"likes": 0, "shares": 0, "comments": 0}, "stumbledupon": {"shares": 0}}, "site_full": "www.devonlive.com", "main_image": "https://i2-prod.devonlive.com/incoming/article1702826.ece/ALTERNATES/s1200/Question-Time-is-coming-to-Exeter.jpg", "site_section": "http://www.westernmorningnews.co.uk/editorschoices.rss", "section_title": "Devon Live - frontpage", "url": "https://www.devonlive.com/news/question-time-coming-exeter-next-1702822", "country": "GB", "title": "Question time is coming to Exeter next week: How to get in the audience", "performance_score": 0, "site": "devonlive.com", "participants_count": 1, "title_full": "", "spam_score": 0.0, "site_type": "news", "published": "2018-06-22T01:21:00.000+03:00", "replies_count": 0, "uuid": "884497dee1537cc5b882130a2795dfa456af91d6"}, "author": "Richard Booth", "url": "https://www.devonlive.com/news/question-time-coming-exeter-next-1702822", "ord_in_thread": 0, "title": "Question time is coming to Exeter next week: How to get in the audience", "locations": [], "entities": {"persons": [{"name": "tim martin", "sentiment": "none"}, {"name": "david dimbleby", "sentiment": "none"}, {"name": "wetherspoons", "sentiment": "none"}], "locations": [{"name": "exeter", "sentiment": "none"}, {"name": "uk", "sentiment": "none"}, {"name": "streatham", "sentiment": "none"}, {"name": "brexit", "sentiment": "none"}, {"name": "devon", "sentiment": "none"}, {"name": "birmingham", "sentiment": "none"}], "organizations": [{"name": "exeter share bbc", "sentiment": "none"}, {"name": "exeter northcott theatre", "sentiment": "none"}, {"name": "university of exeter", "sentiment": "none"}]}, "highlightText": "", "language": "english", "persons": [], "text": "Question Time is coming to Exeter Share Thank you for subscribing!\nBBC politics show Question Time is coming to Exeter next week and audience members are wanted for the show.\nThe show will be at Exeter Northcott Theatre, Streatham Campus, University of Exeter on Thursday 28th.\nThe Exeter visit follows the show being presented from Birmingham on the 21 – with Exeter resident and Wetherspoons boss Tim Martin appearing on the panel.\nIt will be the last time David Dimbleby will be hosting the show in Exeter after announcing he will leave at the end of the year – after 25 years.\nProducers are now keen for people in the local area to apply to be part of the show in the audience. Read More Government accused of dirty tricks in bid to win vital Brexit deal vote - Devon MPs react\nDavid Dimbleby said: \"I am very much looking forward to bringing Question Time to Exeter. What really matters is that we have a lively audience who want to speak their mind. It’s a chance for people in Exeter to get their voice heard not just by politicians, but right across the UK.”\nWhat you need to know\n· People from Exeter and the surrounding area can apply to be part of the audience via the website: bbc.co.uk/questiontime or by phone: 0330 123 9988\n· Question Time is the nation’s most popular political debate programme, on BBC One, Thursdays, 10:45pm\n· There are approximately 100 people in the audience, selected to ensure political balance\n· Question Time always has representation from the government of the day and the official opposition party, as well as representatives from other political parties. The rest of the panel is made-up of political commentators and well-known public figures Read More A strong case to legalise cannabis and take crime off the streets\nFacts:\n· Question Time began on Tuesday 25 September 1979 and David Dimbleby has been presenting the programme since 1994\n· This will be Question Time’s sixth visit to Exeter. The last visit was in April 2016, with Liam Fox, Paddy Ashdown, Kate Hoey, Leanne Wood and Tim Martin on the panel. Like us on Facebook", "external_links": ["https://comm-proxy.tm-awx.com/api/publications/devonlive/subscriptions/&quot;}", "http://bbc.co.uk/questiontime"], "published": "2018-06-22T01:21:00.000+03:00", "crawled": "2018-06-22T01:31:35.046+03:00", "highlightTitle": ""}