{"organizations": [], "uuid": "967c2f60985029461da9f43a4666d4d0a8a2582d", "thread": {"social": {"gplus": {"shares": 0}, "pinterest": {"shares": 0}, "vk": {"shares": 0}, "linkedin": {"shares": 0}, "facebook": {"likes": 0, "shares": 0, "comments": 0}, "stumbledupon": {"shares": 0}}, "site_full": "www.devonlive.com", "main_image": "http://www.devonlive.com/images/localworld/ugc-images/276269/Article/images/30338004/16005309.jpg", "site_section": "", "section_title": "", "url": "http://www.devonlive.com/students-baffled-by-bizarre-biology-gcse-exam-question/story-30338004-detail/story.html", "country": "US", "title": "Students baffled by bizarre Darwin monkey biology GCSE exam question | Devon Live", "performance_score": 0, "site": "devonlive.com", "participants_count": 0, "title_full": "", "spam_score": 0.224, "site_type": "news", "published": "2017-05-17T20:34:00.000+03:00", "replies_count": 0, "uuid": "967c2f60985029461da9f43a4666d4d0a8a2582d"}, "author": "Carl Eve At Plymouth Herald", "url": "http://www.devonlive.com/students-baffled-by-bizarre-biology-gcse-exam-question/story-30338004-detail/story.html", "ord_in_thread": 0, "title": "Students baffled by bizarre Darwin monkey biology GCSE exam question | Devon Live", "locations": [], "entities": {"persons": [{"name": "darwin", "sentiment": "none"}, {"name": "dawlish", "sentiment": "none"}, {"name": "don", "sentiment": "none"}, {"name": "lina", "sentiment": "none"}, {"name": "r.f simpson", "sentiment": "none"}, {"name": "kathy selden", "sentiment": "none"}, {"name": "cosmo brown", "sentiment": "none"}, {"name": "devon", "sentiment": "none"}, {"name": "don lockwood", "sentiment": "none"}, {"name": "lina lamont", "sentiment": "none"}], "locations": [{"name": "exeter", "sentiment": "none"}, {"name": "killerton estate", "sentiment": "none"}, {"name": "hele", "sentiment": "none"}, {"name": "dartington", "sentiment": "none"}, {"name": "brexit", "sentiment": "none"}, {"name": "new devon", "sentiment": "none"}, {"name": "south west", "sentiment": "none"}, {"name": "south devon", "sentiment": "none"}], "organizations": [{"name": "dartington food fair", "sentiment": "none"}, {"name": "nhs", "sentiment": "none"}, {"name": "dawlish musical theatre company", "sentiment": "none"}]}, "highlightText": "", "language": "english", "persons": [], "text": "Public urged to 'remain vigilant' after Exeter burglary \nPolice are appealing for witnesses after thieves entered a property in Exeter through a window and took belongings and cash. The burglary happened at a residential property on the Killerton Estate, in the Hele area of Exeter. Thieves entered the home through an insecure window sometime between 2pm and 2.45pm on May 11, while the resident was out. The offender managed to escape having taken a handbag containing cash and cards from the kitchen table. Police are urging residents in the Hele area of Exeter to remain vigilant. \nDawlish will be singing in the rain this week \nThe Dawlish Musical Theatre Company have certainly excelled themselves with this hilarious and lively musical. Singing in the Rain tells the story of Don Lockwood who is a silent movie star. His leading lady, Lina Lamont, is head over heels in love with him but he does not feel the same. With the first talking picture The Jazz Singer being such a success, the head of the studio, R.F Simpson, decides he has to compete and makes The Duelling Cavalier into a talking film. The problem arises when Lina cannot sing and has a very annoying accent. Don's best friend Cosmo Brown comes up with the idea to overdub her voice with a novice actress called Kathy Selden. \nDevon expert on immigration as an election issue \nDuring this general election, as with the 2016 EU referendum that set off the chain of events leading to it, immigration is likely to play a key role. Research by the British Election Study into what mattered most to referendum voters demonstrated that leavers were primarily concerned about sovereignty and immigration. A recent ComRes/Sunday Mirror poll suggested that immigration was fourth in the list of issues most important to voters in the South West – behind the NHS, Brexit, and the economy; the Brexit option likely incorporates many such concerns. \nNew Devon gin to be launched at food fair \nA brand new gin, created in South Devon using local ingredients will be launched at Dartington Food Fair. Elmhirst Gin will officially be launched at the food fair which takes place over the bank holiday weekend (May 28 and 29) and will be available to buy both at The Shops at Dartington and online. Created at Dartington, using ingredients from the estate, this new premium gin blends tradition with a modern twist to produce a unique taste.", "external_links": [], "published": "2017-05-17T20:34:00.000+03:00", "crawled": "2017-05-17T16:12:37.000+03:00", "highlightTitle": ""}